README.rst
setup.py
hackerearth/__init__.py
hackerearth/api_handlers.py
hackerearth/parameters.py
hackerearth/result.py
hackerearth/settings.py
hackerearth/test_api.py
he_sdk_python.egg-info/PKG-INFO
he_sdk_python.egg-info/SOURCES.txt
he_sdk_python.egg-info/dependency_links.txt
he_sdk_python.egg-info/top_level.txt