Metadata-Version: 1.1
Name: he-sdk-python
Version: 0.3
Summary: Python client for HackerEarth Code Checker API v3
Home-page: https://github.com/HackerEarth/he-sdk-python
Author: Praveen Kumar
Author-email: praveen@hackerearth.com
License: MIT
Keywords: hackerarth code cheker api python client
Platform: UNKNOWN
Classifier: Development Status :: 4 - Beta
Classifier: Intended Audience :: Developers
Classifier: Topic :: Internet
Classifier: License :: OSI Approved :: MIT License
Classifier: Programming Language :: Python :: 2.6
Classifier: Programming Language :: Python :: 2.7
